coolpy/__init__.py
coolpy/_mymath.cpp
coolpy/_mymath.cpython-310-darwin.so
coolpy/elliptic_integrals.py
coolpy/nelder_mead.cpp
coolpy/rk4_beta.cpp
coolpy/Logo/coolpy_logo.png
coolpy-0.0.80.dist-info/METADATA
coolpy-0.0.80.dist-info/WHEEL
coolpy-0.0.80.dist-info/top_level.txt
coolpy-0.0.80.dist-info/RECORD
